fast_eval/__init__.py
fast_eval/__main__.py
fast_eval/fast_eval.py
fast_eval/util.py
fast_eval-0.1.6.dist-info/LICENSE
fast_eval-0.1.6.dist-info/METADATA
fast_eval-0.1.6.dist-info/WHEEL
fast_eval-0.1.6.dist-info/entry_points.txt
fast_eval-0.1.6.dist-info/top_level.txt
fast_eval-0.1.6.dist-info/RECORD
