Metadata-Version: 2.1
Name: fast-eval
Version: 0.1.6
Summary: Simple tool to provide automation to assessment processes.
Home-page: https://github.com/Virgile-Dauge/fast-eval
Author: Virgile Daugé
Author-email: virgile.dauge@pm.me
License: UNKNOWN
Keywords: assessment,evaluation
Platform: UNKNOWN
Classifier: Development Status :: 4 - Beta
Classifier: Environment :: Console
Classifier: Intended Audience :: Developers
Classifier: License :: OSI Approved :: GNU General Public License v3 (GPLv3)
Classifier: Operating System :: POSIX
Classifier: Programming Language :: Python :: 3.6
Requires-Python: >=3.6
Requires-Dist: colored
